setup.py
zakupki_saver_models/__init__.py
zakupki_saver_models/company.py
zakupki_saver_models/complete_lot.py
zakupki_saver_models/lot.py
zakupki_saver_models/record.py
zakupki_saver_models/representative.py
zakupki_saver_models/supervisor.py
zakupki_saver_models/tender.py
zakupki_saver_models.egg-info/PKG-INFO
zakupki_saver_models.egg-info/SOURCES.txt
zakupki_saver_models.egg-info/dependency_links.txt
zakupki_saver_models.egg-info/requires.txt
zakupki_saver_models.egg-info/top_level.txt